{
  "annotations": {
    "list": [
      {
        "builtIn": 1,
        "datasource": "-- Grafana --",
        "enable": true,
        "hide": true,
        "iconColor": "rgba(0, 211, 255, 1)",
        "name": "Annotations & Alerts",
        "type": "dashboard"
      }
    ]
  },
  "editable": true,
  "gnetId": null,
  "graphTooltip": 0,
  "id": 47,
  "iteration": 1634104168004,
  "links": [],
  "panels": [
    {
      "cacheTimeout": null,
      "datasource": "Prometheus",
      "description": "Busy state of all CPU cores together (5 min average)",
      "fieldConfig": {
        "defaults": {
          "color": {
            "mode": "thresholds"
          },
          "mappings": [
            {
              "id": 0,
              "op": "=",
              "text": "N/A",
              "type": 1,
              "value": "null"
            }
          ],
          "max": 100,
          "min": 0,
          "thresholds": {
            "mode": "absolute",
            "steps": [
              {
                "color": "rgba(50, 172, 45, 0.97)",
                "value": null
              },
              {
                "color": "rgba(237, 129, 40, 0.89)",
                "value": 85
              },
              {
                "color": "rgba(245, 54, 54, 0.9)",
                "value": 95
              }
            ]
          },
          "unit": "percent"
        },
        "overrides": []
      },
      "gridPos": {
        "h": 5,
        "w": 6,
        "x": 0,
        "y": 0
      },
      "id": 2,
      "links": [],
      "maxPerRow": 4,
      "options": {
        "orientation": "horizontal",
        "reduceOptions": {
          "calcs": [
            "lastNotNull"
          ],
          "fields": "",
          "values": false
        },
        "showThresholdLabels": false,
        "showThresholdMarkers": true,
        "text": {}
      },
      "pluginVersion": "7.5.7",
      "repeat": "job",
      "repeatDirection": "h",
      "scopedVars": {
        "job": {
          "selected": false,
          "text": "Ubuntu_Server_metrics",
          "value": "Ubuntu_Server_metrics"
        }
      },
      "targets": [
        {
          "expr": "avg(node_load5{job=\"$job\"}) /  count(count(node_cpu_seconds_total{job=\"$job\"}) by (cpu)) * 100",
          "format": "time_series",
          "hide": false,
          "interval": "",
          "intervalFactor": 1,
          "legendFormat": "",
          "refId": "A",
          "step": 900
        }
      ],
      "title": "$job",
      "type": "gauge"
    },
    {
      "cacheTimeout": null,
      "datasource": "Prometheus",
      "description": "Busy state of all CPU cores together (5 min average)",
      "fieldConfig": {
        "defaults": {
          "color": {
            "mode": "thresholds"
          },
          "mappings": [
            {
              "id": 0,
              "op": "=",
              "text": "N/A",
              "type": 1,
              "value": "null"
            }
          ],
          "max": 100,
          "min": 0,
          "thresholds": {
            "mode": "absolute",
            "steps": [
              {
                "color": "rgba(50, 172, 45, 0.97)",
                "value": null
              },
              {
                "color": "rgba(237, 129, 40, 0.89)",
                "value": 85
              },
              {
                "color": "rgba(245, 54, 54, 0.9)",
                "value": 95
              }
            ]
          },
          "unit": "percent"
        },
        "overrides": []
      },
      "gridPos": {
        "h": 5,
        "w": 6,
        "x": 6,
        "y": 0
      },
      "id": 3,
      "links": [],
      "maxPerRow": 4,
      "options": {
        "orientation": "horizontal",
        "reduceOptions": {
          "calcs": [
            "lastNotNull"
          ],
          "fields": "",
          "values": false
        },
        "showThresholdLabels": false,
        "showThresholdMarkers": true,
        "text": {}
      },
      "pluginVersion": "7.5.7",
      "repeatDirection": "h",
      "repeatIteration": 1634104168004,
      "repeatPanelId": 2,
      "scopedVars": {
        "job": {
          "selected": false,
          "text": "Physical Server-ISVHPR",
          "value": "Physical Server-ISVHPR"
        }
      },
      "targets": [
        {
          "expr": "avg(node_load5{job=\"$job\"}) /  count(count(node_cpu_seconds_total{job=\"$job\"}) by (cpu)) * 100",
          "format": "time_series",
          "hide": false,
          "interval": "",
          "intervalFactor": 1,
          "legendFormat": "",
          "refId": "A",
          "step": 900
        }
      ],
      "title": "$job",
      "type": "gauge"
    },
    {
      "cacheTimeout": null,
      "datasource": "Prometheus",
      "description": "Busy state of all CPU cores together (5 min average)",
      "fieldConfig": {
        "defaults": {
          "color": {
            "mode": "thresholds"
          },
          "mappings": [
            {
              "id": 0,
              "op": "=",
              "text": "N/A",
              "type": 1,
              "value": "null"
            }
          ],
          "max": 100,
          "min": 0,
          "thresholds": {
            "mode": "absolute",
            "steps": [
              {
                "color": "rgba(50, 172, 45, 0.97)",
                "value": null
              },
              {
                "color": "rgba(237, 129, 40, 0.89)",
                "value": 85
              },
              {
                "color": "rgba(245, 54, 54, 0.9)",
                "value": 95
              }
            ]
          },
          "unit": "percent"
        },
        "overrides": []
      },
      "gridPos": {
        "h": 5,
        "w": 6,
        "x": 12,
        "y": 0
      },
      "id": 4,
      "links": [],
      "maxPerRow": 4,
      "options": {
        "orientation": "horizontal",
        "reduceOptions": {
          "calcs": [
            "lastNotNull"
          ],
          "fields": "",
          "values": false
        },
        "showThresholdLabels": false,
        "showThresholdMarkers": true,
        "text": {}
      },
      "pluginVersion": "7.5.7",
      "repeatDirection": "h",
      "repeatIteration": 1634104168004,
      "repeatPanelId": 2,
      "scopedVars": {
        "job": {
          "selected": false,
          "text": "Physical Server-ISVHDQ",
          "value": "Physical Server-ISVHDQ"
        }
      },
      "targets": [
        {
          "expr": "avg(node_load5{job=\"$job\"}) /  count(count(node_cpu_seconds_total{job=\"$job\"}) by (cpu)) * 100",
          "format": "time_series",
          "hide": false,
          "interval": "",
          "intervalFactor": 1,
          "legendFormat": "",
          "refId": "A",
          "step": 900
        }
      ],
      "title": "$job",
      "type": "gauge"
    },
    {
      "cacheTimeout": null,
      "datasource": "Prometheus",
      "description": "Busy state of all CPU cores together (5 min average)",
      "fieldConfig": {
        "defaults": {
          "color": {
            "mode": "thresholds"
          },
          "mappings": [
            {
              "id": 0,
              "op": "=",
              "text": "N/A",
              "type": 1,
              "value": "null"
            }
          ],
          "max": 100,
          "min": 0,
          "thresholds": {
            "mode": "absolute",
            "steps": [
              {
                "color": "rgba(50, 172, 45, 0.97)",
                "value": null
              },
              {
                "color": "rgba(237, 129, 40, 0.89)",
                "value": 85
              },
              {
                "color": "rgba(245, 54, 54, 0.9)",
                "value": 95
              }
            ]
          },
          "unit": "percent"
        },
        "overrides": []
      },
      "gridPos": {
        "h": 5,
        "w": 6,
        "x": 18,
        "y": 0
      },
      "id": 5,
      "links": [],
      "maxPerRow": 4,
      "options": {
        "orientation": "horizontal",
        "reduceOptions": {
          "calcs": [
            "lastNotNull"
          ],
          "fields": "",
          "values": false
        },
        "showThresholdLabels": false,
        "showThresholdMarkers": true,
        "text": {}
      },
      "pluginVersion": "7.5.7",
      "repeatDirection": "h",
      "repeatIteration": 1634104168004,
      "repeatPanelId": 2,
      "scopedVars": {
        "job": {
          "selected": false,
          "text": "VM-ISVIOT",
          "value": "VM-ISVIOT"
        }
      },
      "targets": [
        {
          "expr": "avg(node_load5{job=\"$job\"}) /  count(count(node_cpu_seconds_total{job=\"$job\"}) by (cpu)) * 100",
          "format": "time_series",
          "hide": false,
          "interval": "",
          "intervalFactor": 1,
          "legendFormat": "",
          "refId": "A",
          "step": 900
        }
      ],
      "title": "$job",
      "type": "gauge"
    },
    {
      "cacheTimeout": null,
      "datasource": "Prometheus",
      "description": "Busy state of all CPU cores together (5 min average)",
      "fieldConfig": {
        "defaults": {
          "color": {
            "mode": "thresholds"
          },
          "mappings": [
            {
              "id": 0,
              "op": "=",
              "text": "N/A",
              "type": 1,
              "value": "null"
            }
          ],
          "max": 100,
          "min": 0,
          "thresholds": {
            "mode": "absolute",
            "steps": [
              {
                "color": "rgba(50, 172, 45, 0.97)",
                "value": null
              },
              {
                "color": "rgba(237, 129, 40, 0.89)",
                "value": 85
              },
              {
                "color": "rgba(245, 54, 54, 0.9)",
                "value": 95
              }
            ]
          },
          "unit": "percent"
        },
        "overrides": []
      },
      "gridPos": {
        "h": 5,
        "w": 6,
        "x": 0,
        "y": 5
      },
      "id": 6,
      "links": [],
      "maxPerRow": 4,
      "options": {
        "orientation": "horizontal",
        "reduceOptions": {
          "calcs": [
            "lastNotNull"
          ],
          "fields": "",
          "values": false
        },
        "showThresholdLabels": false,
        "showThresholdMarkers": true,
        "text": {}
      },
      "pluginVersion": "7.5.7",
      "repeatDirection": "h",
      "repeatIteration": 1634104168004,
      "repeatPanelId": 2,
      "scopedVars": {
        "job": {
          "selected": false,
          "text": "VM-ISVDEV",
          "value": "VM-ISVDEV"
        }
      },
      "targets": [
        {
          "expr": "avg(node_load5{job=\"$job\"}) /  count(count(node_cpu_seconds_total{job=\"$job\"}) by (cpu)) * 100",
          "format": "time_series",
          "hide": false,
          "interval": "",
          "intervalFactor": 1,
          "legendFormat": "",
          "refId": "A",
          "step": 900
        }
      ],
      "title": "$job",
      "type": "gauge"
    },
    {
      "cacheTimeout": null,
      "datasource": "Prometheus",
      "description": "Busy state of all CPU cores together (5 min average)",
      "fieldConfig": {
        "defaults": {
          "color": {
            "mode": "thresholds"
          },
          "mappings": [
            {
              "id": 0,
              "op": "=",
              "text": "N/A",
              "type": 1,
              "value": "null"
            }
          ],
          "max": 100,
          "min": 0,
          "thresholds": {
            "mode": "absolute",
            "steps": [
              {
                "color": "rgba(50, 172, 45, 0.97)",
                "value": null
              },
              {
                "color": "rgba(237, 129, 40, 0.89)",
                "value": 85
              },
              {
                "color": "rgba(245, 54, 54, 0.9)",
                "value": 95
              }
            ]
          },
          "unit": "percent"
        },
        "overrides": []
      },
      "gridPos": {
        "h": 5,
        "w": 6,
        "x": 6,
        "y": 5
      },
      "id": 7,
      "links": [],
      "maxPerRow": 4,
      "options": {
        "orientation": "horizontal",
        "reduceOptions": {
          "calcs": [
            "lastNotNull"
          ],
          "fields": "",
          "values": false
        },
        "showThresholdLabels": false,
        "showThresholdMarkers": true,
        "text": {}
      },
      "pluginVersion": "7.5.7",
      "repeatDirection": "h",
      "repeatIteration": 1634104168004,
      "repeatPanelId": 2,
      "scopedVars": {
        "job": {
          "selected": false,
          "text": "VM-ISVFID",
          "value": "VM-ISVFID"
        }
      },
      "targets": [
        {
          "expr": "avg(node_load5{job=\"$job\"}) /  count(count(node_cpu_seconds_total{job=\"$job\"}) by (cpu)) * 100",
          "format": "time_series",
          "hide": false,
          "interval": "",
          "intervalFactor": 1,
          "legendFormat": "",
          "refId": "A",
          "step": 900
        }
      ],
      "title": "$job",
      "type": "gauge"
    },
    {
      "cacheTimeout": null,
      "datasource": "Prometheus",
      "description": "Busy state of all CPU cores together (5 min average)",
      "fieldConfig": {
        "defaults": {
          "color": {
            "mode": "thresholds"
          },
          "mappings": [
            {
              "id": 0,
              "op": "=",
              "text": "N/A",
              "type": 1,
              "value": "null"
            }
          ],
          "max": 100,
          "min": 0,
          "thresholds": {
            "mode": "absolute",
            "steps": [
              {
                "color": "rgba(50, 172, 45, 0.97)",
                "value": null
              },
              {
                "color": "rgba(237, 129, 40, 0.89)",
                "value": 85
              },
              {
                "color": "rgba(245, 54, 54, 0.9)",
                "value": 95
              }
            ]
          },
          "unit": "percent"
        },
        "overrides": []
      },
      "gridPos": {
        "h": 5,
        "w": 6,
        "x": 12,
        "y": 5
      },
      "id": 8,
      "links": [],
      "maxPerRow": 4,
      "options": {
        "orientation": "horizontal",
        "reduceOptions": {
          "calcs": [
            "lastNotNull"
          ],
          "fields": "",
          "values": false
        },
        "showThresholdLabels": false,
        "showThresholdMarkers": true,
        "text": {}
      },
      "pluginVersion": "7.5.7",
      "repeatDirection": "h",
      "repeatIteration": 1634104168004,
      "repeatPanelId": 2,
      "scopedVars": {
        "job": {
          "selected": false,
          "text": "VM-ISVFIP",
          "value": "VM-ISVFIP"
        }
      },
      "targets": [
        {
          "expr": "avg(node_load5{job=\"$job\"}) /  count(count(node_cpu_seconds_total{job=\"$job\"}) by (cpu)) * 100",
          "format": "time_series",
          "hide": false,
          "interval": "",
          "intervalFactor": 1,
          "legendFormat": "",
          "refId": "A",
          "step": 900
        }
      ],
      "title": "$job",
      "type": "gauge"
    },
    {
      "cacheTimeout": null,
      "datasource": "Prometheus",
      "description": "Busy state of all CPU cores together (5 min average)",
      "fieldConfig": {
        "defaults": {
          "color": {
            "mode": "thresholds"
          },
          "mappings": [
            {
              "id": 0,
              "op": "=",
              "text": "N/A",
              "type": 1,
              "value": "null"
            }
          ],
          "max": 100,
          "min": 0,
          "thresholds": {
            "mode": "absolute",
            "steps": [
              {
                "color": "rgba(50, 172, 45, 0.97)",
                "value": null
              },
              {
                "color": "rgba(237, 129, 40, 0.89)",
                "value": 85
              },
              {
                "color": "rgba(245, 54, 54, 0.9)",
                "value": 95
              }
            ]
          },
          "unit": "percent"
        },
        "overrides": []
      },
      "gridPos": {
        "h": 5,
        "w": 6,
        "x": 18,
        "y": 5
      },
      "id": 9,
      "links": [],
      "maxPerRow": 4,
      "options": {
        "orientation": "horizontal",
        "reduceOptions": {
          "calcs": [
            "lastNotNull"
          ],
          "fields": "",
          "values": false
        },
        "showThresholdLabels": false,
        "showThresholdMarkers": true,
        "text": {}
      },
      "pluginVersion": "7.5.7",
      "repeatDirection": "h",
      "repeatIteration": 1634104168004,
      "repeatPanelId": 2,
      "scopedVars": {
        "job": {
          "selected": false,
          "text": "VM-ISVPRD",
          "value": "VM-ISVPRD"
        }
      },
      "targets": [
        {
          "expr": "avg(node_load5{job=\"$job\"}) /  count(count(node_cpu_seconds_total{job=\"$job\"}) by (cpu)) * 100",
          "format": "time_series",
          "hide": false,
          "interval": "",
          "intervalFactor": 1,
          "legendFormat": "",
          "refId": "A",
          "step": 900
        }
      ],
      "title": "$job",
      "type": "gauge"
    },
    {
      "cacheTimeout": null,
      "datasource": "Prometheus",
      "description": "Busy state of all CPU cores together (5 min average)",
      "fieldConfig": {
        "defaults": {
          "color": {
            "mode": "thresholds"
          },
          "mappings": [
            {
              "id": 0,
              "op": "=",
              "text": "N/A",
              "type": 1,
              "value": "null"
            }
          ],
          "max": 100,
          "min": 0,
          "thresholds": {
            "mode": "absolute",
            "steps": [
              {
                "color": "rgba(50, 172, 45, 0.97)",
                "value": null
              },
              {
                "color": "rgba(237, 129, 40, 0.89)",
                "value": 85
              },
              {
                "color": "rgba(245, 54, 54, 0.9)",
                "value": 95
              }
            ]
          },
          "unit": "percent"
        },
        "overrides": []
      },
      "gridPos": {
        "h": 5,
        "w": 6,
        "x": 0,
        "y": 10
      },
      "id": 10,
      "links": [],
      "maxPerRow": 4,
      "options": {
        "orientation": "horizontal",
        "reduceOptions": {
          "calcs": [
            "lastNotNull"
          ],
          "fields": "",
          "values": false
        },
        "showThresholdLabels": false,
        "showThresholdMarkers": true,
        "text": {}
      },
      "pluginVersion": "7.5.7",
      "repeatDirection": "h",
      "repeatIteration": 1634104168004,
      "repeatPanelId": 2,
      "scopedVars": {
        "job": {
          "selected": false,
          "text": "VM-ISVQAS",
          "value": "VM-ISVQAS"
        }
      },
      "targets": [
        {
          "expr": "avg(node_load5{job=\"$job\"}) /  count(count(node_cpu_seconds_total{job=\"$job\"}) by (cpu)) * 100",
          "format": "time_series",
          "hide": false,
          "interval": "",
          "intervalFactor": 1,
          "legendFormat": "",
          "refId": "A",
          "step": 900
        }
      ],
      "title": "$job",
      "type": "gauge"
    },
    {
      "cacheTimeout": null,
      "datasource": "Prometheus",
      "description": "Busy state of all CPU cores together (5 min average)",
      "fieldConfig": {
        "defaults": {
          "color": {
            "mode": "thresholds"
          },
          "mappings": [
            {
              "id": 0,
              "op": "=",
              "text": "N/A",
              "type": 1,
              "value": "null"
            }
          ],
          "max": 100,
          "min": 0,
          "thresholds": {
            "mode": "absolute",
            "steps": [
              {
                "color": "rgba(50, 172, 45, 0.97)",
                "value": null
              },
              {
                "color": "rgba(237, 129, 40, 0.89)",
                "value": 85
              },
              {
                "color": "rgba(245, 54, 54, 0.9)",
                "value": 95
              }
            ]
          },
          "unit": "percent"
        },
        "overrides": []
      },
      "gridPos": {
        "h": 5,
        "w": 6,
        "x": 6,
        "y": 10
      },
      "id": 11,
      "links": [],
      "maxPerRow": 4,
      "options": {
        "orientation": "horizontal",
        "reduceOptions": {
          "calcs": [
            "lastNotNull"
          ],
          "fields": "",
          "values": false
        },
        "showThresholdLabels": false,
        "showThresholdMarkers": true,
        "text": {}
      },
      "pluginVersion": "7.5.7",
      "repeatDirection": "h",
      "repeatIteration": 1634104168004,
      "repeatPanelId": 2,
      "scopedVars": {
        "job": {
          "selected": false,
          "text": "VM-ISVSOL",
          "value": "VM-ISVSOL"
        }
      },
      "targets": [
        {
          "expr": "avg(node_load5{job=\"$job\"}) /  count(count(node_cpu_seconds_total{job=\"$job\"}) by (cpu)) * 100",
          "format": "time_series",
          "hide": false,
          "interval": "",
          "intervalFactor": 1,
          "legendFormat": "",
          "refId": "A",
          "step": 900
        }
      ],
      "title": "$job",
      "type": "gauge"
    }
  ],
  "schemaVersion": 27,
  "style": "dark",
  "tags": [],
  "templating": {
    "list": [
      {
        "allValue": null,
        "current": {
          "selected": false,
          "text": "All",
          "value": "$__all"
        },
        "datasource": null,
        "definition": "label_values(node_uname_info, job)",
        "description": null,
        "error": null,
        "hide": 0,
        "includeAll": true,
        "label": "job",
        "multi": false,
        "name": "job",
        "options": [
          {
            "selected": true,
            "text": "All",
            "value": "$__all"
          },
          {
            "selected": false,
            "text": "Ubuntu_Server_metrics",
            "value": "Ubuntu_Server_metrics"
          },
          {
            "selected": false,
            "text": "Physical Server-ISVHPR",
            "value": "Physical Server-ISVHPR"
          },
          {
            "selected": false,
            "text": "Physical Server-ISVHDQ",
            "value": "Physical Server-ISVHDQ"
          },
          {
            "selected": false,
            "text": "VM-ISVIOT",
            "value": "VM-ISVIOT"
          },
          {
            "selected": false,
            "text": "VM-ISVDEV",
            "value": "VM-ISVDEV"
          },
          {
            "selected": false,
            "text": "VM-ISVFID",
            "value": "VM-ISVFID"
          },
          {
            "selected": false,
            "text": "VM-ISVFIP",
            "value": "VM-ISVFIP"
          },
          {
            "selected": false,
            "text": "VM-ISVPRD",
            "value": "VM-ISVPRD"
          },
          {
            "selected": false,
            "text": "VM-ISVQAS",
            "value": "VM-ISVQAS"
          },
          {
            "selected": false,
            "text": "VM-ISVSOL",
            "value": "VM-ISVSOL"
          }
        ],
        "query": {
          "query": "label_values(node_uname_info, job)",
          "refId": "StandardVariableQuery"
        },
        "refresh": 0,
        "regex": "",
        "skipUrlSync": false,
        "sort": 0,
        "tagValuesQuery": "",
        "tags": [],
        "tagsQuery": "",
        "type": "query",
        "useTags": false
      }
    ]
  },
  "time": {
    "from": "now-6h",
    "to": "now"
  },
  "timepicker": {},
  "timezone": "",
  "title": "13.All Linux CPU dashboard",
  "uid": "ShFSsKknz",
  "version": 5
}
